CSIKit/__init__.py
CSIKit/__main__.py
CSIKit/csi/__init__.py
CSIKit/csi/csidata.py
CSIKit/csi/csiframe.py
CSIKit/csi/csimetadata.py
CSIKit/csi/frames/__init__.py
CSIKit/csi/frames/ath.py
CSIKit/csi/frames/esp.py
CSIKit/csi/frames/feitcsi.py
CSIKit/csi/frames/iwl.py
CSIKit/csi/frames/mvm.py
CSIKit/csi/frames/nex.py
CSIKit/csi/frames/usr.py
CSIKit/filters/__init__.py
CSIKit/filters/passband.py
CSIKit/filters/statistical.py
CSIKit/filters/wavelets/__init__.py
CSIKit/filters/wavelets/dwt.py
CSIKit/reader/__init__.py
CSIKit/reader/reader.py
CSIKit/reader/reader_selector.py
CSIKit/reader/readers/__init__.py
CSIKit/reader/readers/read_atheros.py
CSIKit/reader/readers/read_bfee.py
CSIKit/reader/readers/read_csv.py
CSIKit/reader/readers/read_feitcsi.py
CSIKit/reader/readers/read_pcap.py
CSIKit/reader/readers/read_pico.py
CSIKit/reader/readers/pico/AbstractPicoScenesFrameSegment.py
CSIKit/reader/readers/pico/CSISegment.py
CSIKit/reader/readers/pico/ExtraInfoSegment.py
CSIKit/reader/readers/pico/FrameContainer.py
CSIKit/reader/readers/pico/MVMExtraSegment.py
CSIKit/reader/readers/pico/ModularPicoScenesFrame.py
CSIKit/reader/readers/pico/RxSBasicSegment.py
CSIKit/reader/readers/pico/__init__.py
CSIKit/tools/__init__.py
CSIKit/tools/batch_graph.py
CSIKit/tools/convert_csv.py
CSIKit/tools/convert_json.py
CSIKit/tools/convert_npz.py
CSIKit/tools/get_info.py
CSIKit/util/__init__.py
CSIKit/util/byteops.py
CSIKit/util/constants.py
CSIKit/util/csitools.py
CSIKit/util/errors.py
CSIKit/util/filters.py
CSIKit/util/matlab.py
CSIKit/util/stringops.py
CSIKit/visualization/__init__.py
CSIKit/visualization/graph.py
CSIKit/visualization/metric.py
CSIKit/visualization/plot_scenario.py
CSIKit-2.5.dist-info/LICENSE.txt
CSIKit-2.5.dist-info/METADATA
CSIKit-2.5.dist-info/WHEEL
CSIKit-2.5.dist-info/entry_points.txt
CSIKit-2.5.dist-info/top_level.txt
CSIKit-2.5.dist-info/RECORD
