Metadata-Version: 2.1
Name: CSIKit
Version: 2.5
Summary: Tools for extracting Channel State Information from files produced by a range of WiFi hardware/drivers.
Home-page: https://github.com/Gi-z/CSIKit/
Author: Glenn Forbes
Author-email: g.r.forbes@rgu.ac.uk
Keywords: csi,csi-data,csi-extraction-suite,csi-parsing,intel,visualisation,wifi-hardware
Classifier: Development Status :: 4 - Beta
Classifier: Intended Audience :: Science/Research
Classifier: Programming Language :: Python :: 3.6
Classifier: Programming Language :: Python :: 3.7
Classifier: Programming Language :: Python :: 3.8
Classifier: Programming Language :: Python :: 3.9
Classifier: Topic :: Scientific/Engineering
Requires-Python: >=3.8
License-File: LICENSE.txt
Requires-Dist: matplotlib
Requires-Dist: scikit-learn
Requires-Dist: pandas
Requires-Dist: PyWavelets
Requires-Dist: numpy
